gcbrickwork/Bytes_Helper.py
gcbrickwork/JMP.py
gcbrickwork/PRM.py
gcbrickwork/__init__.py
gcbrickwork-3.0.4.dist-info/licenses/LICENSE
unit_tests/__init__.py
unit_tests/test_jmp.py
gcbrickwork-3.0.4.dist-info/METADATA
gcbrickwork-3.0.4.dist-info/WHEEL
gcbrickwork-3.0.4.dist-info/top_level.txt
gcbrickwork-3.0.4.dist-info/RECORD
