Metadata-Version: 2.4
Name: gcbrickwork
Version: 3.0.4
Summary: A library of tools to read various GameCube files
Home-page: https://github.com/SomeJakeGuy/gcbrickwork
Author: Some Jake Guy
Author-email: somejakeguy@gmail.com
License: MIT
Keywords: gcbrickwork,gamecube,prm,jmp,gc,gc jmp,gc prm,param,gc param
Classifier: Programming Language :: Python :: 3.12
Classifier: License :: OSI Approved :: MIT License
Classifier: Operating System :: OS Independent
Requires-Python: >=3.12
License-File: LICENSE
Dynamic: author
Dynamic: author-email
Dynamic: classifier
Dynamic: description
Dynamic: description-content-type
Dynamic: home-page
Dynamic: keywords
Dynamic: license
Dynamic: license-file
Dynamic: requires-python
Dynamic: summary
